tfdsio/__init__.py
tfdsio/adapter.py
tfdsio/dataset.py
tfdsio/tft5.py
tfdsio/torch.py
tfdsio/utils.py
tfdsio-0.0.7.dist-info/LICENSE
tfdsio-0.0.7.dist-info/METADATA
tfdsio-0.0.7.dist-info/WHEEL
tfdsio-0.0.7.dist-info/top_level.txt
tfdsio-0.0.7.dist-info/RECORD
