Metadata-Version: 2.1
Name: tfdsio
Version: 0.0.7
Summary: tfdsio
Home-page: http://github.com/trisongz/tfdsio
Author: Tri Songz
Author-email: ts@growthengineai.com
License: UNKNOWN
Platform: UNKNOWN
Classifier: Development Status :: 3 - Alpha
Classifier: Environment :: Console
Classifier: Intended Audience :: Developers
Requires-Python: >=3.6
Requires-Dist: tensorflow (>=1.15.0)
Requires-Dist: tensorflow-datasets (>=4.2.0)
Requires-Dist: file-io (>=0.1.0)
Requires-Dist: seqio
Requires-Dist: t5
Requires-Dist: sentencepiece
Provides-Extra: t5
Requires-Dist: t5 ; extra == 't5'
Requires-Dist: seqio ; extra == 't5'
Provides-Extra: transformers
Requires-Dist: transformers ; extra == 'transformers'
Requires-Dist: sentencepiece ; extra == 'transformers'
